[
	{
		"id": "sort",
		"title": "Sort",
		"type": "sort",
		"canAscend": false,
		"options": [
			"Default",
			"Latest Updated",
			"Score",
			"Name A-Z",
			"Release Date",
			"Most Viewed"
		]
	},
	{
		"id": "type",
		"title": "Type",
		"type": "select",
		"options": [
			"All",
			"Manga",
			"One-shot",
			"Doujinshi",
			"Light Novel",
			"Manhwa",
			"Manhua",
			"Comic"
		],
		"ids": ["", "1", "2", "3", "4", "5", "6", "8"]
	},
	{
		"id": "status",
		"title": "Status",
		"type": "select",
		"options": [
			"All",
			"Finished",
			"Publishing",
			"On Hiatus",
			"Discontinued",
			"Not yet published"
		],
		"ids": ["", "1", "2", "3", "4", "5"]
	},
	{
		"id": "rating_type",
		"title": "Rating Type",
		"type": "select",
		"options": [
			"All",
			"G - All Ages",
			"PG - Children",
			"PG-13 - Teens 13 or older",
			"R - 17+ (violence & profanity)",
			"R+ - Mild Nudity",
			"Rx - Hentai"
		],
		"ids": ["", "1", "2", "3", "4", "5", "6"]
	},
	{
		"id": "score",
		"title": "Score",
		"type": "select",
		"options": [
			"All",
			"(1) Apalling",
			"(2) Horrible",
			"(3) Very Bad",
			"(4) Bad",
			"(5) Average",
			"(6) Fine",
			"(7) Good",
			"(8) Very Good",
			"(9) Great",
			"(10) Masterpiece"
		],
		"ids": ["", "1", "2", "3", "4", "5", "6", "8", "9", "10"]
	},
	{
		"id": "genre",
		"title": "Genres",
		"type": "multi-select",
		"isGenre": true,
		"options": [
			"Action",
			"Adventure",
			"Cars",
			"Comedy",
			"Dementia",
			"Demons",
			"Doujinshi",
			"Drama",
			"Ecchi",
			"Fantasy",
			"Game",
			"Gender Bender",
			"Harem",
			"Hentai",
			"Historical",
			"Horror",
			"Josei",
			"Kids",
			"Magic",
			"Martial Arts",
			"Mecha",
			"Military",
			"Music",
			"Mystery",
			"Parody",
			"Police",
			"Psychological",
			"Romance",
			"Samurai",
			"School",
			"Sci-Fi",
			"Seinen",
			"Shoujo",
			"Shoujo Ai",
			"Shounen",
			"Shounen Ai",
			"Slice of Life",
			"Space",
			"Sports",
			"Super Power",
			"Supernatural",
			"Thriller",
			"Vampire",
			"Yaoi",
			"Yuri"
		],
		"ids": [
			"1",
			"2",
			"3",
			"4",
			"5",
			"6",
			"7",
			"8",
			"9",
			"10",
			"11",
			"12",
			"13",
			"14",
			"15",
			"16",
			"17",
			"18",
			"19",
			"20",
			"21",
			"22",
			"23",
			"24",
			"25",
			"26",
			"27",
			"28",
			"29",
			"30",
			"31",
			"32",
			"33",
			"34",
			"35",
			"36",
			"37",
			"38",
			"39",
			"40",
			"41",
			"42",
			"43",
			"44",
			"45"
		]
	}
]
